merkava/__init__.py
merkava/blueprints.py
merkava/channels.py
merkava/server.py
merkava/views.py
merkava-0.3.0.dist-info/DESCRIPTION.rst
merkava-0.3.0.dist-info/METADATA
merkava-0.3.0.dist-info/RECORD
merkava-0.3.0.dist-info/WHEEL
merkava-0.3.0.dist-info/metadata.json
merkava-0.3.0.dist-info/top_level.txt
