Metadata-Version: 2.0
Name: merkava
Version: 0.3.0
Summary: A fast ordered NoSQL datastore.
Home-page: https://github.com/ahopkins/merkava
Author: Adam Hopkins
Author-email: admhpkns@gmail.com
License: MIT
Keywords: merkava
Platform: UNKNOWN
Classifier: Development Status :: 4 - Beta
Classifier: Intended Audience :: Developers
Classifier: License :: OSI Approved :: MIT License
Classifier: Natural Language :: English
Classifier: Programming Language :: Python :: 3.6
